bandwidthestimation/__init__.py
bandwidthestimation/bandwidth_estimation.py
bandwidthestimation-0.1.0.data/data/LICENSE
bandwidthestimation-0.1.0.dist-info/LICENSE
bandwidthestimation-0.1.0.dist-info/METADATA
bandwidthestimation-0.1.0.dist-info/WHEEL
bandwidthestimation-0.1.0.dist-info/top_level.txt
bandwidthestimation-0.1.0.dist-info/RECORD
