Metadata-Version: 2.1
Name: bandwidthestimation
Version: 0.1.0
Summary: Signal processing tool to detect the maximum energy threshold of one or more audio files
Home-page: https://github.com/simonD3V/bandwidthestimation
Author: Simon Devauchelle
Author-email: devausimon@gmail.com
Keywords: energy,bandwidth estimation
Requires-Python: >=3.10.2
License-File: LICENSE
Requires-Dist: numpy
Requires-Dist: scipy
